openweathermap_requests/__init__.py
openweathermap_requests/version.py
openweathermap_requests-0.0.5.dist-info/DESCRIPTION.rst
openweathermap_requests-0.0.5.dist-info/entry_points.txt
openweathermap_requests-0.0.5.dist-info/METADATA
openweathermap_requests-0.0.5.dist-info/metadata.json
openweathermap_requests-0.0.5.dist-info/RECORD
openweathermap_requests-0.0.5.dist-info/top_level.txt
openweathermap_requests-0.0.5.dist-info/WHEEL
