Metadata-Version: 2.0
Name: openweathermap-requests
Version: 0.0.5
Summary: openweathermap requests fetch weather history Pandas DataFrame
Home-page: https://github.com/scls19fr/openweathermap_requests
Author: Sebastien Celles
Author-email: s.celles@gmail.com
License: BSD
Keywords: data weather temperature history
Platform: UNKNOWN
Classifier: Development Status :: 3 - Alpha
Classifier: Environment :: Console
Classifier: Intended Audience :: Science/Research
Classifier: Operating System :: OS Independent
Classifier: Programming Language :: Cython
Classifier: Programming Language :: Python
Classifier: Programming Language :: Python :: 2.7
Classifier: Programming Language :: Python :: 3.3
Classifier: Programming Language :: Python :: 3.4
Classifier: Topic :: Scientific/Engineering
Classifier: License :: OSI Approved :: BSD License
Requires-Dist: pandas
Requires-Dist: requests
Requires-Dist: requests-cache
Requires-Dist: click
Requires-Dist: six
Provides-Extra: dev
Requires-Dist: check-manifest; extra == 'dev'
Requires-Dist: nose; extra == 'dev'
Provides-Extra: test
Requires-Dist: coverage; extra == 'test'
Requires-Dist: nose; extra == 'test'
